Metadata-Version: 2.4
Name: monday
Version: 2.0.4
Summary: A Python client library for Monday.com
Home-page: https://github.com/ProdPerfect/monday
Author: Christina D'Astolfo
Author-email: chdastolfo@gmail.com, lemi@prodperfect.com, pevner@prodperfect.com
License: BSD
Classifier: Programming Language :: Python :: 3
Classifier: Programming Language :: Python :: 3.11
Classifier: Programming Language :: Python :: 3.12
Classifier: Programming Language :: Python :: 3.13
Classifier: Operating System :: OS Independent
Requires-Python: >=3.11
License-File: LICENSE
Requires-Dist: requests>=2.30.0
Dynamic: author
Dynamic: author-email
Dynamic: classifier
Dynamic: description
Dynamic: description-content-type
Dynamic: home-page
Dynamic: license
Dynamic: license-file
Dynamic: requires-dist
Dynamic: requires-python
Dynamic: summary
